etf_steuernotizbuch/__init__.py
etf_steuernotizbuch/main.py
etf_steuernotizbuch/test_main.py
etf_steuernotizbuch-0.2.0.dist-info/licenses/LICENSE
tests/__init__.py
etf_steuernotizbuch-0.2.0.dist-info/METADATA
etf_steuernotizbuch-0.2.0.dist-info/WHEEL
etf_steuernotizbuch-0.2.0.dist-info/entry_points.txt
etf_steuernotizbuch-0.2.0.dist-info/top_level.txt
etf_steuernotizbuch-0.2.0.dist-info/RECORD
