Metadata-Version: 2.4
Name: etf_steuernotizbuch
Version: 0.2.0
Summary: Kleine Software mit GUI zum Verwalten und Simulieren der Steuerzahlungen auf Gewinne und Vorabpauschalen von Fonds und ETFs unter deutschem Steuerrecht. Besonders geeignet für Auslandsdepots und zur Simulation der anfallenden Steuern bei einem beabsichtigten Verkauf von Anteilen.
Home-page: https://github.com/just1436/etf-steuernotizbuch
Author: just1436
Author-email: ju.sto@mailbox.org
License: MIT
Keywords: etf steuer notizbuch vorabpauschale tax germany deutschland
Classifier: Development Status :: 3 - Alpha
Classifier: Topic :: Utilities
License-File: LICENSE
Requires-Dist: matplotlib
Requires-Dist: numpy
Requires-Dist: tkcalendar
Dynamic: author
Dynamic: author-email
Dynamic: classifier
Dynamic: description
Dynamic: description-content-type
Dynamic: home-page
Dynamic: keywords
Dynamic: license
Dynamic: license-file
Dynamic: requires-dist
Dynamic: summary
